veerum_sdk-5.2.0-py3.8-nspkg.pth
veerum/cli/__init__.py
veerum/cli/common.py
veerum/cli/debug.py
veerum/cli/retcode.py
veerum/cli/version.py
veerum/cli/annotations/__init__.py
veerum/cli/annotations/delete.py
veerum/cli/annotations/find.py
veerum/cli/annotations/inspect.py
veerum/cli/automations/__init__.py
veerum/cli/automations/relationship.py
veerum/cli/automations/sync.py
veerum/cli/files/__init__.py
veerum/cli/files/delete.py
veerum/cli/files/download.py
veerum/cli/files/find.py
veerum/cli/files/inspect.py
veerum/cli/files/update.py
veerum/cli/files/upload.py
veerum/cli/jobs/__init__.py
veerum/cli/jobs/misplaced_objects.py
veerum/cli/jobs/populate_keys.py
veerum/cli/jobs/warn_inactive_users.py
veerum/cli/metadata/__init__.py
veerum/cli/metadata/find.py
veerum/cli/metadata/inspect.py
veerum/cli/metadata/keys/__init__.py
veerum/cli/metadata/keys/add.py
veerum/cli/metadata/keys/clear.py
veerum/cli/metadata/keys/find.py
veerum/cli/metadata/keys/set.py
veerum/cli/metadata/upload/__init__.py
veerum/cli/metadata/upload/csvparser.py
veerum/cli/milestones/__init__.py
veerum/cli/milestones/create.py
veerum/cli/milestones/delete.py
veerum/cli/milestones/find.py
veerum/cli/milestones/inspect.py
veerum/cli/milestones/update.py
veerum/cli/models/__init__.py
veerum/cli/models/delete.py
veerum/cli/models/find.py
veerum/cli/models/inspect.py
veerum/cli/models/update.py
veerum/cli/models/download/__init__.py
veerum/cli/models/metadata/__init__.py
veerum/cli/models/metadata/delete.py
veerum/cli/models/metadata/set.py
veerum/cli/models/upload/__helpers.py
veerum/cli/models/upload/__init__.py
veerum/cli/models/upload/potree.py
veerum/cli/models/upload/potree2.py
veerum/cli/models/upload/tiles.py
veerum/cli/models/upload/unity.py
veerum/cli/objects/__init__.py
veerum/cli/objects/delete.py
veerum/cli/objects/deleteone.py
veerum/cli/objects/fileparser.py
veerum/cli/objects/find.py
veerum/cli/objects/ingest.py
veerum/cli/objects/inspect.py
veerum/cli/objects/update.py
veerum_sdk-5.2.0.dist-info/METADATA
veerum_sdk-5.2.0.dist-info/WHEEL
veerum_sdk-5.2.0.dist-info/entry_points.txt
veerum_sdk-5.2.0.dist-info/namespace_packages.txt
veerum_sdk-5.2.0.dist-info/top_level.txt
veerum_sdk-5.2.0.dist-info/RECORD
