Metadata-Version: 2.1
Name: veerum-sdk
Version: 5.2.0
Summary: SDK & CLI for interacting with the Veerum API
Home-page: https://github.com/Veerum/veerum-sdk
Author: Veerum Inc.
Author-email: info@veerum.com
Classifier: Development Status :: 2 - Pre-Alpha
Classifier: Operating System :: OS Independent
Classifier: Programming Language :: Python :: 3
Classifier: Programming Language :: Python :: 3.7
Requires-Python: >=3.7
Requires-Dist: tornado (>=5.1.1)
Requires-Dist: tqdm (>=4.31.1)
Requires-Dist: backports-datetime-fromisoformat (>=1.0.0)
Requires-Dist: tuspy (==0.2.5)
